fastuseragent-1.0.5.data/purelib/fastuseragent/__init__.py
fastuseragent-1.0.5.data/purelib/fastuseragent/libuseragent.h
fastuseragent-1.0.5.data/purelib/fastuseragent/libuseragent.so
fastuseragent-1.0.5.data/purelib/fastuseragent/parse_user_agent.py
fastuseragent-1.0.5.dist-info/LICENSE
fastuseragent-1.0.5.dist-info/METADATA
fastuseragent-1.0.5.dist-info/WHEEL
fastuseragent-1.0.5.dist-info/top_level.txt
fastuseragent-1.0.5.dist-info/RECORD
